odoo10_addon_web_search_autocomplete_prefetch-10.0.1.0.0.99.dev5-py3.8-nspkg.pth
odoo/addons/web_search_autocomplete_prefetch/README.rst
odoo/addons/web_search_autocomplete_prefetch/__init__.py
odoo/addons/web_search_autocomplete_prefetch/__manifest__.py
odoo/addons/web_search_autocomplete_prefetch/i18n/es.po
odoo/addons/web_search_autocomplete_prefetch/i18n/fi.po
odoo/addons/web_search_autocomplete_prefetch/i18n/sl.po
odoo/addons/web_search_autocomplete_prefetch/i18n/tr.po
odoo/addons/web_search_autocomplete_prefetch/i18n/web_search_autocomplete_prefetch.pot
odoo/addons/web_search_autocomplete_prefetch/images/web_search_autocomplete_prefetch.png
odoo/addons/web_search_autocomplete_prefetch/readme/CONFIGURE.rst
odoo/addons/web_search_autocomplete_prefetch/readme/CONTRIBUTORS.rst
odoo/addons/web_search_autocomplete_prefetch/readme/DESCRIPTION.rst
odoo/addons/web_search_autocomplete_prefetch/static/description/icon.png
odoo/addons/web_search_autocomplete_prefetch/static/description/index.html
odoo/addons/web_search_autocomplete_prefetch/static/src/js/web_search_autocomplete_prefetch.js
odoo/addons/web_search_autocomplete_prefetch/views/base_view.xml
odoo/addons/web_search_autocomplete_prefetch/views/templates.xml
odoo10_addon_web_search_autocomplete_prefetch-10.0.1.0.0.99.dev5.dist-info/METADATA
odoo10_addon_web_search_autocomplete_prefetch-10.0.1.0.0.99.dev5.dist-info/WHEEL
odoo10_addon_web_search_autocomplete_prefetch-10.0.1.0.0.99.dev5.dist-info/namespace_packages.txt
odoo10_addon_web_search_autocomplete_prefetch-10.0.1.0.0.99.dev5.dist-info/top_level.txt
odoo10_addon_web_search_autocomplete_prefetch-10.0.1.0.0.99.dev5.dist-info/RECORD
